Metadata-Version: 1.2
Name: taskpl
Version: 0.1.0
Summary: task pipeline for human
Home-page: https://github.com/williamfzc/taskpl
Author: williamfzc
Author-email: fengzc@vip.qq.com
License: MIT
Platform: UNKNOWN
Classifier: License :: OSI Approved :: MIT License
Classifier: Programming Language :: Python
Classifier: Programming Language :: Python :: 3
Requires-Python: >=3.6
